tmp/alu.v
module alu (overflow,alu_out,zero,src_a,src_b,opcode,reset,clk) ;

output  reg overflow;
output  reg zero ;
output  reg [3:0]alu_out ;
input[3:0] src_a,src_b;
input[2:0]opcode ;
input reset,clk;

always @(*) begin
    case(opcode)
      3'b000:alu_out  = 4'b0000;
      3'b001:alu_out  = (src_a & src_b);
      3'b010:alu_out  = (src_a |src_b);
      3'b011:alu_out  = src_a;
      3'b100:alu_out  = src_a+src_b;
      3'b101:alu_out  = src_a-src_b;
      3'b110:alu_out  = src_a>>src_b;
      3'b111:alu_out= src_a<<src_b;
      default:alu_out=4'b0000;
    endcase
end

always@(*)begin
  zero=~(|alu_out);
  end
  
always@(*)begin
  case(opcode)
    3'b100: overflow=((src_a[3]^alu_out[3])&(src_b[3]^alu_out[3]))?1'b1:1'b0;
    3'b101: overflow=((src_a[3]^alu_out[3])&~(src_b[3]^alu_out[3]))?1'b1:1'b0;
    default overflow=1'b0;
  endcase
end

endmodule

tmp/testfixture.v
//#######################################################################################
/*+++++++++++++++++++++++++++++++++++++++++++++++++++++++++++++++++++++++++++++++++++++++
 
 * Software             :Simulation with ncverilog
 * File                 :ALU.v
 * Author               :Chia-Yang Lin
 * School               :Department of Engineering Science , NCKU
 * Date                 :2011/07/15
 * Lab                  :VLSI signal processing LAB @ LAB 41206 
 * Version              :1
 * Abstract             :
 * Modification History :    
			 

//+++++++++++++++++++++++++++++++++++++++++++++++++++++++++++++++++++++++++++++++++++++++
//#######################################################################################*/


`define DATA_NUM 509
`define CYCLE 10
`define PATTERN "pattern_in.txt"
`define EXPECT "alu_out.txt"
`timescale 1ns/10ps

module testfixture ;

reg [2:0] opcode;

reg [3:0] src_a ,src_b ; 

reg clk,reset ;

wire [3:0]alu_out ;

wire overflow,zero ;

reg [10:0]pattern_in[0:`DATA_NUM-1] ;

reg [5:0]ans[0:`DATA_NUM-1] ;


reg overflow_exp,zero_exp ;

reg [3:0] alu_out_exp ;

alu u_alu (	.overflow(overflow),
			.alu_out(alu_out),
			.zero(zero),
			.src_a(src_a),
			.src_b(src_b),
			.opcode(opcode),
			.clk(clk),
			.reset(reset)
) ;

always begin #(`CYCLE/2) clk=~clk ; end  //clock generation

initial begin
$readmemb(`PATTERN,pattern_in) ;
$readmemb(`EXPECT,ans) ;
end


integer i ,err ,check;

initial begin
clk=1'b0 ;
err=0 ;
check=0;
@(negedge clk) reset=1'b1 ;
#(`CYCLE*2) reset=1'b0 ;

@(negedge clk) ;

  for(i=0;i<`DATA_NUM;i=i+1) begin
    {opcode,src_a,src_b}=pattern_in[i] ;
    {alu_out_exp,overflow_exp,zero_exp}=ans[i] ;
    @(negedge clk) ;
//@(posedge clk) ;
    if(alu_out!=alu_out_exp||overflow!=overflow_exp||zero!=zero_exp) begin
    err=err+1 ;
    $display($time,"Error at opcode=%b, src_a=%b, src_b=%b",opcode,src_a,src_b) ;
    $display($time,"Expect   : alu_out=%b, overflow=%b, zero=%b",alu_out_exp,overflow_exp,zero_exp) ;
    $display($time,"Your ans : alu_out=%b, overflow=%b, zero=%b\n\n",alu_out,overflow,zero) ;	
	

    end
    else if(alu_out==alu_out_exp&&overflow==overflow_exp&&zero==zero_exp) check=check+1;
  end
end



initial
begin
   $dumpfile("alu.vcd");
   $dumpvars;
end


initial begin

#(`CYCLE*100) 
if((err==0)&&(check==96)) begin
$display("-------------------   ALU check successfully   -------------------");
$display("            $$              ");
$display("           $  $");
$display("           $  $");
$display("          $   $");
$display("         $    $");
$display("$$$$$$$$$     $$$$$$$$");
$display("$$$$$$$              $");
$display("$$$$$$$              $");
$display("$$$$$$$              $");
$display("$$$$$$$              $");
$display("$$$$$$$              $");
$display("$$$$$$$$$$$$         $$");
$display("$$$$$      $$$$$$$$$$");
end
else if((err==0)&&(check!=96)) begin
$display("-----------   Oops! Something wrong with your code!   ------------");
end
else $display("-------------------   There are %d errors   -------------------", err);
$finish ;

end

endmodule

tmp/alu.vcd
$date
	Fri Apr 11 20:36:30 2025
$end
$version
	Icarus Verilog
$end
$timescale
	10ps
$end
$scope module testfixture $end
$var wire 1 ! zero $end
$var wire 1 " overflow $end
$var wire 4 # alu_out [3:0] $end
$var reg 4 $ alu_out_exp [3:0] $end
$var reg 1 % clk $end
$var reg 3 & opcode [2:0] $end
$var reg 1 ' overflow_exp $end
$var reg 1 ( reset $end
$var reg 4 ) src_a [3:0] $end
$var reg 4 * src_b [3:0] $end
$var reg 1 + zero_exp $end
$var integer 32 , check [31:0] $end
$var integer 32 - err [31:0] $end
$var integer 32 . i [31:0] $end
$scope module u_alu $end
$var wire 1 % clk $end
$var wire 3 / opcode [2:0] $end
$var wire 1 ( reset $end
$var wire 4 0 src_a [3:0] $end
$var wire 4 1 src_b [3:0] $end
$var reg 4 2 alu_out [3:0] $end
$var reg 1 " overflow $end
$var reg 1 ! zero $end
$upscope $end
$upscope $end
$enddefinitions $end
#0
$dumpvars
bx 2
bx 1
bx 0
bx /
bx .
b0 -
b0 ,
x+
bx *
bx )
x(
x'
bx &
0%
bx $
bx #
x"
x!
$end
#500
1%
#1000
1(
0%
#1500
1%
#2000
0%
#2500
1%
#3000
0!
0"
b1010 #
b1010 2
b1010 $
0'
0+
b100 &
b100 /
b1 )
b1 0
b1001 *
b1001 1
b0 .
0%
0(
#3500
1%
#4000
b1101 #
b1101 2
b1101 $
b11 &
b11 /
b1101 )
b1101 0
b1101 *
b1101 1
b1 .
b1 ,
0%
#4500
1%
#5000
b1 #
b1 2
b1 $
b101 &
b101 /
b10 )
b10 0
b1 *
b1 1
b10 .
b10 ,
0%
#5500
1%
#6000
1"
b1001 #
b1001 2
b1001 $
1'
b110 )
b110 0
b1101 *
b1101 1
b11 .
b11 ,
0%
#6500
1%
#7000
0"
b11 #
b11 2
b11 $
0'
b1100 )
b1100 0
b1001 *
b1001 1
b100 .
b100 ,
0%
#7500
1%
#8000
1!
b0 #
b0 2
b0 $
1+
b110 &
b110 /
b101 )
b101 0
b1010 *
b1010 1
b101 .
b101 ,
0%
#8500
1%
#9000
0!
b101 #
b101 2
b101 $
0+
b101 &
b101 /
b111 )
b111 0
b10 *
b10 1
b110 .
b110 ,
0%
#9500
1%
#10000
1!
b0 #
b0 2
b0 $
1+
b111 &
b111 /
b10 )
b10 0
b1110 *
b1110 1
b111 .
b111 ,
0%
#10500
1%
#11000
b0 &
b0 /
b101 )
b101 0
b1100 *
b1100 1
b1000 .
b1000 ,
0%
#11500
1%
#12000
0!
b1000 #
b1000 2
b1000 $
0+
b101 &
b101 /
b1101 )
b1101 0
b101 *
b101 1
b1001 .
b1001 ,
0%
#12500
1%
#13000
b1010 #
b1010 2
b1010 $
b11 &
b11 /
b1010 )
b1010 0
b0 *
b0 1
b1010 .
b1010 ,
0%
#13500
1%
#14000
1!
b0 #
b0 2
b0 $
1+
b0 &
b0 /
b1101 *
b1101 1
b1011 .
b1011 ,
0%
#14500
1%
#15000
b110 &
b110 /
b11 )
b11 0
b1100 .
b1100 ,
0%
#15500
1%
#16000
0!
b1011 #
b1011 2
b1011 $
0+
b11 &
b11 /
b1011 )
b1011 0
b101 *
b101 1
b1101 .
b1101 ,
0%
#16500
1%
#17000
b1111 #
b1111 2
b1111 $
b10 &
b10 /
b1110 )
b1110 0
b1101 *
b1101 1
b1110 .
b1110 ,
0%
#17500
1%
#18000
1!
b0 #
b0 2
b0 $
1+
b111 &
b111 /
b11 )
b11 0
b1010 *
b1010 1
b1111 .
b1111 ,
0%
#18500
1%
#19000
0!
b1110 #
b1110 2
b1110 $
0+
b10 &
b10 /
b1100 )
b1100 0
b10 *
b10 1
b10000 .
b10000 ,
0%
#19500
1%
#20000
b1001 #
b1001 2
b1001 $
b1 )
b1 0
b1000 *
b1000 1
b10001 .
b10001 ,
0%
#20500
1%
#21000
1!
b0 #
b0 2
b0 $
1+
b0 &
b0 /
b1001 )
b1001 0
b1011 *
b1011 1
b10010 .
b10010 ,
0%
#21500
1%
#22000
b110 &
b110 /
b110 )
b110 0
b1110 *
b1110 1
b10011 .
b10011 ,
0%
#22500
1%
#23000
0!
1"
b101 #
b101 2
b101 $
1'
0+
b100 &
b100 /
b1010 )
b1010 0
b1011 *
b1011 1
b10100 .
b10100 ,
0%
#23500
1%
#24000
0"
0'
b1 &
b1 /
b101 )
b101 0
b1111 *
b1111 1
b10101 .
b10101 ,
0%
#24500
1%
#25000
b1010 #
b1010 2
b1010 $
b11 &
b11 /
b1010 )
b1010 0
b1110 *
b1110 1
b10110 .
b10110 ,
0%
#25500
1%
#26000
1"
b1000 #
b1000 2
b1000 $
1'
b101 &
b101 /
b1 )
b1 0
b1001 *
b1001 1
b10111 .
b10111 ,
0%
#26500
1%
#27000
0"
b1111 #
b1111 2
b1111 $
0'
b10 &
b10 /
b1100 )
b1100 0
b1111 *
b1111 1
b11000 .
b11000 ,
0%
#27500
1%
#28000
1!
b0 #
b0 2
b0 $
1+
b111 &
b111 /
b1000 )
b1000 0
b111 *
b111 1
b11001 .
b11001 ,
0%
#28500
1%
#29000
b1100 )
b1100 0
b1011 *
b1011 1
b11010 .
b11010 ,
0%
#29500
1%
#30000
b1 &
b1 /
b1001 )
b1001 0
b0 *
b0 1
b11011 .
b11011 ,
0%
#30500
1%
#31000
b111 &
b111 /
b1 )
b1 0
b110 *
b110 1
b11100 .
b11100 ,
0%
#31500
1%
#32000
0!
b1010 #
b1010 2
b1010 $
0+
b100 &
b100 /
b10 )
b10 0
b1000 *
b1000 1
b11101 .
b11101 ,
0%
#32500
1%
#33000
b100 #
b100 2
b100 $
b111 &
b111 /
b1101 )
b1101 0
b10 *
b10 1
b11110 .
b11110 ,
0%
#33500
1%
#34000
1!
b0 #
b0 2
b0 $
1+
b110 &
b110 /
b1001 *
b1001 1
b11111 .
b11111 ,
0%
#34500
1%
#35000
b111 &
b111 /
b11 )
b11 0
b101 *
b101 1
b100000 .
b100000 ,
0%
#35500
1%
#36000
b0 &
b0 /
b1011 )
b1011 0
b1001 *
b1001 1
b100001 .
b100001 ,
0%
#36500
1%
#37000
b111 &
b111 /
b1010 )
b1010 0
b1000 *
b1000 1
b100010 .
b100010 ,
0%
#37500
1%
#38000
b110 &
b110 /
b1110 )
b1110 0
b1100 *
b1100 1
b100011 .
b100011 ,
0%
#38500
1%
#39000
0!
b111 #
b111 2
b111 $
0+
b10 &
b10 /
b110 )
b110 0
b11 *
b11 1
b100100 .
b100100 ,
0%
#39500
1%
#40000
b1111 #
b1111 2
b1111 $
b11 &
b11 /
b1111 )
b1111 0
b100101 .
b100101 ,
0%
#40500
1%
#41000
1!
b0 #
b0 2
b0 $
1+
b111 &
b111 /
b100 )
b100 0
b111 *
b111 1
b100110 .
b100110 ,
0%
#41500
1%
#42000
0!
b110 #
b110 2
b110 $
0+
b11 &
b11 /
b110 )
b110 0
b1010 *
b1010 1
b100111 .
b100111 ,
0%
#42500
1%
#43000
b1000 #
b1000 2
b1000 $
b1 &
b1 /
b1101 )
b1101 0
b101000 .
b101000 ,
0%
#43500
1%
#44000
b110 #
b110 2
b110 $
b101 &
b101 /
b101 )
b101 0
b1111 *
b1111 1
b101001 .
b101001 ,
0%
#44500
1%
#45000
1!
b0 #
b0 2
b0 $
1+
b1 &
b1 /
b100 )
b100 0
b0 *
b0 1
b101010 .
b101010 ,
0%
#45500
1%
#46000
0!
b1111 #
b1111 2
b1111 $
0+
b10 &
b10 /
b1011 )
b1011 0
b1110 *
b1110 1
b101011 .
b101011 ,
0%
#46500
1%
#47000
1"
b111 #
b111 2
b111 $
1'
b100 &
b100 /
b1010 )
b1010 0
b1101 *
b1101 1
b101100 .
b101100 ,
0%
#47500
1%
#48000
0"
b110 #
b110 2
b110 $
0'
b11 &
b11 /
b110 )
b110 0
b1110 *
b1110 1
b101101 .
b101101 ,
0%
#48500
1%
#49000
1!
b0 #
b0 2
b0 $
1+
b111 &
b111 /
b1010 )
b1010 0
b110 *
b110 1
b101110 .
b101110 ,
0%
#49500
1%
#50000
b0 &
b0 /
b1001 )
b1001 0
b1000 *
b1000 1
b101111 .
b101111 ,
0%
#50500
1%
#51000
0!
b111 #
b111 2
b111 $
0+
b100 &
b100 /
b11 )
b11 0
b100 *
b100 1
b110000 .
b110000 ,
0%
#51500
1%
#52000
b1001 #
b1001 2
b1001 $
b1 &
b1 /
b1011 )
b1011 0
b1101 *
b1101 1
b110001 .
b110001 ,
0%
#52500
1%
#53000
b100 #
b100 2
b100 $
b1101 )
b1101 0
b110 *
b110 1
b110010 .
b110010 ,
0%
#53500
1%
#54000
b111 #
b111 2
b111 $
b10 &
b10 /
b110 )
b110 0
b101 *
b101 1
b110011 .
b110011 ,
0%
#54500
1%
#55000
1!
b0 #
b0 2
b0 $
1+
b110 &
b110 /
b100 )
b100 0
b111 *
b111 1
b110100 .
b110100 ,
0%
#55500
1%
#56000
b1 &
b1 /
b1000 *
b1000 1
b110101 .
b110101 ,
0%
#56500
1%
#57000
b0 &
b0 /
b1101 )
b1101 0
b111 *
b111 1
b110110 .
b110110 ,
0%
#57500
1%
#58000
b110 &
b110 /
b1000 )
b1000 0
b1100 *
b1100 1
b110111 .
b110111 ,
0%
#58500
1%
#59000
0!
b1101 #
b1101 2
b1101 $
0+
b101 &
b101 /
b1001 )
b1001 0
b111000 .
b111000 ,
0%
#59500
1%
#60000
1!
b0 #
b0 2
b0 $
1+
b110 &
b110 /
b1010 )
b1010 0
b1101 *
b1101 1
b111001 .
b111001 ,
0%
#60500
1%
#61000
b0 )
b0 0
b11 *
b11 1
b111010 .
b111010 ,
0%
#61500
1%
#62000
0!
b1110 #
b1110 2
b1110 $
0+
b10 &
b10 /
b1110 )
b1110 0
b1010 *
b1010 1
b111011 .
b111011 ,
0%
#62500
1%
#63000
b1 #
b1 2
b1 $
b101 &
b101 /
b1010 )
b1010 0
b1001 *
b1001 1
b111100 .
b111100 ,
0%
#63500
1%
#64000
b110 #
b110 2
b110 $
b111 &
b111 /
b110 )
b110 0
b0 *
b0 1
b111101 .
b111101 ,
0%
#64500
1%
#65000
1!
b0 #
b0 2
b0 $
1+
b110 &
b110 /
b1101 *
b1101 1
b111110 .
b111110 ,
0%
#65500
1%
#66000
0!
b1110 #
b1110 2
b1110 $
0+
b100 &
b100 /
b1000 *
b1000 1
b111111 .
b111111 ,
0%
#66500
1%
#67000
1!
b0 #
b0 2
b0 $
1+
b110 &
b110 /
b1011 )
b1011 0
b1111 *
b1111 1
b1000000 .
b1000000 ,
0%
#67500
1%
#68000
b1 &
b1 /
b1010 )
b1010 0
b1 *
b1 1
b1000001 .
b1000001 ,
0%
#68500
1%
#69000
b111 &
b111 /
b1 )
b1 0
b110 *
b110 1
b1000010 .
b1000010 ,
0%
#69500
1%
#70000
b0 &
b0 /
b101 )
b101 0
b101 *
b101 1
b1000011 .
b1000011 ,
0%
#70500
1%
#71000
0!
b1 #
b1 2
b1 $
0+
b1 &
b1 /
b1 )
b1 0
b1000100 .
b1000100 ,
0%
#71500
1%
#72000
1!
b0 #
b0 2
b0 $
1+
b0 &
b0 /
b1011 )
b1011 0
b11 *
b11 1
b1000101 .
b1000101 ,
0%
#72500
1%
#73000
0!
b1000 #
b1000 2
b1000 $
0+
b100 &
b100 /
b1010 )
b1010 0
b1110 *
b1110 1
b1000110 .
b1000110 ,
0%
#73500
1%
#74000
1!
b0 #
b0 2
b0 $
1+
b0 &
b0 /
b1001 )
b1001 0
b1 *
b1 1
b1000111 .
b1000111 ,
0%
#74500
1%
#75000
b110 &
b110 /
b110 )
b110 0
b1111 *
b1111 1
b1001000 .
b1001000 ,
0%
#75500
1%
#76000
0!
b1111 #
b1111 2
b1111 $
0+
b10 &
b10 /
b1010 )
b1010 0
b1101 *
b1101 1
b1001001 .
b1001001 ,
0%
#76500
1%
#77000
1!
b0 #
b0 2
b0 $
1+
b110 &
b110 /
b1000 )
b1000 0
b1001 *
b1001 1
b1001010 .
b1001010 ,
0%
#77500
1%
#78000
b0 &
b0 /
b1010 )
b1010 0
b11 *
b11 1
b1001011 .
b1001011 ,
0%
#78500
1%
#79000
0!
b111 #
b111 2
b111 $
0+
b11 &
b11 /
b111 )
b111 0
b110 *
b110 1
b1001100 .
b1001100 ,
0%
#79500
1%
#80000
b1101 #
b1101 2
b1101 $
b10 &
b10 /
b100 )
b100 0
b1001 *
b1001 1
b1001101 .
b1001101 ,
0%
#80500
1%
#81000
b1111 #
b1111 2
b1111 $
b1111 *
b1111 1
b1001110 .
b1001110 ,
0%
#81500
1%
#82000
b10 #
b10 2
b10 $
b110 &
b110 /
b1010 )
b1010 0
b10 *
b10 1
b1001111 .
b1001111 ,
0%
#82500
1%
#83000
b1101 #
b1101 2
b1101 $
b10 &
b10 /
b1101 )
b1101 0
b100 *
b100 1
b1010000 .
b1010000 ,
0%
#83500
1%
#84000
1"
b11 #
b11 2
b11 $
1'
b100 &
b100 /
b1010 )
b1010 0
b1001 *
b1001 1
b1010001 .
b1010001 ,
0%
#84500
1%
#85000
0"
b1010 #
b1010 2
b1010 $
0'
b1 &
b1 /
b1110 )
b1110 0
b1011 *
b1011 1
b1010010 .
b1010010 ,
0%
#85500
1%
#86000
b1111 #
b1111 2
b1111 $
b11 &
b11 /
b1111 )
b1111 0
b1001 *
b1001 1
b1010011 .
b1010011 ,
0%
#86500
1%
#87000
1!
b0 #
b0 2
b0 $
1+
b110 &
b110 /
b101 )
b101 0
b1111 *
b1111 1
b1010100 .
b1010100 ,
0%
#87500
1%
#88000
0!
b1000 #
b1000 2
b1000 $
0+
b11 &
b11 /
b1000 )
b1000 0
b1110 *
b1110 1
b1010101 .
b1010101 ,
0%
#88500
1%
#89000
b10 #
b10 2
b10 $
b10 )
b10 0
b1000 *
b1000 1
b1010110 .
b1010110 ,
0%
#89500
1%
#90000
b1001 #
b1001 2
b1001 $
b101 &
b101 /
b1011 )
b1011 0
b10 *
b10 1
b1010111 .
b1010111 ,
0%
#90500
1%
#91000
1!
b0 #
b0 2
b0 $
1+
b110 &
b110 /
b1101 )
b1101 0
b1100 *
b1100 1
b1011000 .
b1011000 ,
0%
#91500
1%
#92000
b0 &
b0 /
b1 )
b1 0
b110 *
b110 1
b1011001 .
b1011001 ,
0%
#92500
1%
#93000
0!
b1000 #
b1000 2
b1000 $
0+
b1 &
b1 /
b1011 )
b1011 0
b1000 *
b1000 1
b1011010 .
b1011010 ,
0%
#93500
1%
#94000
b110 #
b110 2
b110 $
b11 &
b11 /
b110 )
b110 0
b1011 *
b1011 1
b1011011 .
b1011011 ,
0%
#94500
1%
#95000
b111 #
b111 2
b111 $
b10 &
b10 /
b100 )
b100 0
b11 *
b11 1
b1011100 .
b1011100 ,
0%
#95500
1%
#96000
1!
b0 #
b0 2
b0 $
1+
b0 &
b0 /
b10 )
b10 0
b1000 *
b1000 1
b1011101 .
b1011101 ,
0%
#96500
1%
#97000
0!
b1 #
b1 2
b1 $
0+
b1 &
b1 /
b101 )
b101 0
b1 *
b1 1
b1011110 .
b1011110 ,
0%
#97500
1%
#98000
b11 &
b11 /
b1 )
b1 0
b1000 *
b1000 1
b1011111 .
b1011111 ,
0%
#98500
1%
#99000
1!
b0 #
b0 2
b0 $
1+
b111 &
b111 /
b1111 *
b1111 1
b1100000 .
b1100000 ,
0%
#99500
1%
#100000
0!
b1110 #
b1110 2
b1110 $
0+
b100 &
b100 /
b1000 )
b1000 0
b110 *
b110 1
b1100001 .
b1100001 ,
0%
